ACS.ipynb
ACS_simplified.ipynb
COMPAS.ipynb
Diagram.jpg
Readme.md
Tabular.py
__init__.py
logo.png
requirements.txt
setup.py
baselines/basemethod.py
baselines/compare_confidence.py
baselines/lce_surrogate.py
baselines/mix_of_exps.py
datasetsdefer/__init__.py
datasetsdefer/acs_dataset.py
datasetsdefer/basedataset.py
datasetsdefer/broward.py
datasetsdefer/__pycache__/__init__.cpython-310.pyc
datasetsdefer/__pycache__/basedataset.cpython-310.pyc
datasetsdefer/__pycache__/broward.cpython-310.pyc
helpers/__init__.py
helpers/bootstrap.py
helpers/embedding.py
helpers/metrics.py
helpers/utils.py
helpers/__pycache__/metrics.cpython-310.pyc
helpers/__pycache__/utils.cpython-310.pyc
networks/__init__.py
networks/linear_net.py
networks/__pycache__/linear_net.cpython-310.pyc
postprocessing/__init__.py
postprocessing.egg-info/PKG-INFO
postprocessing.egg-info/SOURCES.txt
postprocessing.egg-info/dependency_links.txt
postprocessing.egg-info/requires.txt
postprocessing.egg-info/top_level.txt
training/__init__.py
training/training.py