Metadata-Version: 2.1
Name: postprocessing
Version: 0.1.0
Summary: Multi-Objective Learning via Ensembling
Home-page: https://github.com/AminChrs/PostProces
Author: Amin Charusaie
Author-email: amin.ch90@gmail.com
Classifier: Programming Language :: Python :: 3
Classifier: License :: OSI Approved :: MIT License
Classifier: Operating System :: OS Independent
Requires-Python: >=3.6
